churn_modeling_pipelines/ChurnEvaluator.py
churn_modeling_pipelines/ChurnHypothesisTester.py
churn_modeling_pipelines/ChurnModelBuilder.py
churn_modeling_pipelines/ChurnPlotter.py
churn_modeling_pipelines/ChurnPreprocessor.py
churn_modeling_pipelines/CustomerJourneyClassifier.py
churn_modeling_pipelines/DataPreprocessor.py
churn_modeling_pipelines/EDAHelper.py
churn_modeling_pipelines/EDAPlots.py
churn_modeling_pipelines/EDAReports.py
churn_modeling_pipelines/EnsembleBuilder.py
churn_modeling_pipelines/ModelComparator.py
churn_modeling_pipelines/NeuralNetWrapper.py
churn_modeling_pipelines/__init__.py
churn_modeling_pipelines/utils.py
churn_modeling_pipelines-0.2.26.dist-info/METADATA
churn_modeling_pipelines-0.2.26.dist-info/WHEEL
churn_modeling_pipelines-0.2.26.dist-info/top_level.txt
churn_modeling_pipelines-0.2.26.dist-info/RECORD
